mcp_devtasks/__init__.py
mcp_devtasks/basic_class.py
mcp_devtasks/server.py
mcp_devtasks-0.0.4.dist-info/METADATA
mcp_devtasks-0.0.4.dist-info/WHEEL
mcp_devtasks-0.0.4.dist-info/entry_points.txt
mcp_devtasks-0.0.4.dist-info/licenses/LICENSE
mcp_devtasks-0.0.4.dist-info/RECORD
