Metadata-Version: 2.4
Name: mcp_devtasks
Version: 0.0.4
Summary: A development tasks MCP server for automating install, build, lint, test, and CI commands.
Project-URL: Source, https://github.com/blooop/mcp_devtasks
Project-URL: Home, https://github.com/blooop/mcp_devtasks
Author-email: Austin Gregg-Smith <blooop@gmail.com>
License-Expression: MIT
License-File: LICENSE
Requires-Dist: fastmcp
Requires-Dist: pyyaml
Provides-Extra: test
Requires-Dist: coverage<=7.9.1,>=7.5.4; extra == 'test'
Requires-Dist: hypothesis<=6.135.18,>=6.104.2; extra == 'test'
Requires-Dist: pre-commit<=4.2.0; extra == 'test'
Requires-Dist: pylint<=3.3.7,>=3.2.5; extra == 'test'
Requires-Dist: pytest-cov<=6.2.1,>=4.1; extra == 'test'
Requires-Dist: pytest<=8.4.1,>=7.4; extra == 'test'
Requires-Dist: ruff<=0.12.1,>=0.5.0; extra == 'test'
